wyld_cz/__init__.py
wyld_cz/base.py
wyld_cz/py.typed
wyld_cz/utils.py
wyld_cz-0.1.0.dist-info/WHEEL
wyld_cz-0.1.0.dist-info/entry_points.txt
wyld_cz-0.1.0.dist-info/METADATA
wyld_cz-0.1.0.dist-info/RECORD
