Metadata-Version: 2.3
Name: wyld-cz
Version: 0.1.0
Summary: A custom rules sets for commitizen
Author: zombig
Author-email: zombig <me@zombig.name>
Classifier: Development Status :: 4 - Beta
Classifier: Programming Language :: Python :: 3
Classifier: Programming Language :: Python :: 3.12
Classifier: License :: OSI Approved :: MIT License
Classifier: Operating System :: OS Independent
Requires-Dist: commitizen==3.29.1
Requires-Python: >=3.12
Project-URL: Issues, https://github.com/oberon-systems/wyld-cz/issues
Project-URL: Repository, https://github.com/oberon-systems/wyld-cz
